setup.py
decors/__init__.py
decors/logger.py
descriptors/__init__.py
descriptors/descriptors.py
files/__init__.py
files/server_main.py
jim/__init__.py
jim/config.py
jim/utils.py
loggers/__init__.py
loggers/server_log_config.py
message_server_sheludchenkov.egg-info/PKG-INFO
message_server_sheludchenkov.egg-info/SOURCES.txt
message_server_sheludchenkov.egg-info/dependency_links.txt
message_server_sheludchenkov.egg-info/requires.txt
message_server_sheludchenkov.egg-info/top_level.txt
metaclasses/__init__.py
metaclasses/meta.py
storage/__init__.py
storage/server_db.py