Metadata-Version: 1.0
Name: message-server-sheludchenkov
Version: 0.0.1
Summary: Message Server Sheludchenkov
Home-page: UNKNOWN
Author: Aleksey Sheludchenkov
Author-email: aleshkashell@gmail.com
License: UNKNOWN
Platform: UNKNOWN
